domain/__init__.py
domain/certificate_management.py
domain/contact.py
domain/equipment_management.py
domain/label.py
domain/script_model.py
domain/site.py
domain/switch_management.py
output/__init__.py
output/certificate_shell.py
output/contact_database.py
output/contact_sheet.py
output/database_base.py
output/equipment_shell.py
output/label_database.py
output/script_model_shell.py
output/site_database.py
output/switch_shell.py
aleas-0.0.4.dist-info/METADATA
aleas-0.0.4.dist-info/WHEEL
aleas-0.0.4.dist-info/top_level.txt
aleas-0.0.4.dist-info/RECORD
