Metadata-Version: 2.1
Name: aleas
Version: 0.0.4
Summary: Meilleur projet
Home-page: UNKNOWN
Author: Rmich
Author-email: mohammed.rmich@exnovo.io
License: MIT
Platform: UNKNOWN
Classifier: Programming Language :: Python :: 3
Classifier: License :: OSI Approved :: MIT License
Classifier: Operating System :: OS Independent
Requires-Dist: SQLAlchemy
Requires-Dist: fabric
Requires-Dist: fastapi
Requires-Dist: ldap3
Requires-Dist: openpyxl
Requires-Dist: pandas
Requires-Dist: schedule
Requires-Dist: starlette
Requires-Dist: uvicorn
